therix/__init__.py
therix/alembic/README
therix/alembic/env.py
therix/alembic/script.py.mako
therix/alembic/versions/2024_04_26_0914-739c7981bdd8_added_config_type_for_cache_config.py
therix/alembic/versions/2024_04_26_1644-b8fe483b5a71_add_type_column_in_pipeline_table.py
therix/alembic/versions/2024_05_06_1524-1e7f3dc15e9c_added_chat_history_fix.py
therix/alembic/versions/2024_05_13_1842-f5c4562bcd86_added_config_type_for_system_prompt.py
therix/alembic/versions/2024_05_21_1701-3d84bc32c8ee_changes_type_of_session_id.py
therix/alembic/versions/2024_05_30_1626-1997c3ff664e_added_new_pipeline_type_default.py
therix/alembic/versions/2025_01_25_1200-4443fbd4c9b_add_document_intelligence_config_type.py
therix/alembic/versions/f5fb392e6b0a_initial_database_setup.py
therix/alembic.ini
therix/core/JSONLoader.py
therix/core/__init__.py
therix/core/agent.py
therix/core/cache.py
therix/core/chat_history/base_chat_history.py
therix/core/constants.py
therix/core/data_sources.py
therix/core/document_intelligence_loader.py
therix/core/embedding_models.py
therix/core/inference_models.py
therix/core/output_parser.py
therix/core/output_source.py
therix/core/pii_filter_config.py
therix/core/pipeline.py
therix/core/pipeline_component.py
therix/core/prompt.py
therix/core/response.py
therix/core/summarizer_config.py
therix/core/summarizer_output_model.py
therix/core/system_prompt_config.py
therix/core/therix_RAG.py
therix/core/trace.py
therix/core/version.py
therix/db/__init__.py
therix/db/db_manager.py
therix/db/session.py
therix/db/tests/__init__.py
therix/db/tests/test_db_manager.py
therix/docs/.gitignore
therix/docs/README.md
therix/docs/babel.config.js
therix/docs/blog/2019-05-28-first-blog-post.md
therix/docs/blog/2019-05-29-long-blog-post.md
therix/docs/blog/2021-08-01-mdx-blog-post.mdx
therix/docs/blog/2021-08-26-welcome/docusaurus-plushie-banner.jpeg
therix/docs/blog/2021-08-26-welcome/index.md
therix/docs/blog/authors.yml
therix/docs/docs/LLM-Proxy/_category_.json
therix-0.1.56.dist-info/LICENSE
therix-0.1.56.dist-info/METADATA
therix-0.1.56.dist-info/WHEEL
therix-0.1.56.dist-info/RECORD
